AUTHORS.md
CHANGELOG.md
CONTRIBUTING.md
LICENSE
README.md
imctools/__init__.py
imctools/cli.py
imctools/converters/__init__.py
imctools/converters/exportacquisitioncsv.py
imctools/converters/mcdfolder2imcfolder.py
imctools/converters/ome2analysis.py
imctools/converters/ome2histocat.py
imctools/converters/v1tov2.py
imctools/data/__init__.py
imctools/data/acquisition.py
imctools/data/acquisitiondata.py
imctools/data/channel.py
imctools/data/panorama.py
imctools/data/session.py
imctools/data/slide.py
imctools/io/__init__.py
imctools/io/errors.py
imctools/io/imc/__init__.py
imctools/io/imc/imcparser.py
imctools/io/imc/imcwriter.py
imctools/io/mcd/__init__.py
imctools/io/mcd/constants.py
imctools/io/mcd/mcdparser.py
imctools/io/mcd/mcdxmlparser.py
imctools/io/ometiff/__init__.py
imctools/io/ometiff/ometiffparser.py
imctools/io/txt/__init__.py
imctools/io/txt/txtparser.py
imctools/io/utils.py
imctools-2.1.8.dist-info/entry_points.txt
imctools-2.1.8.dist-info/LICENSE
imctools-2.1.8.dist-info/WHEEL
imctools-2.1.8.dist-info/METADATA
imctools-2.1.8.dist-info/RECORD
