Metadata-Version: 2.1
Name: imctools
Version: 2.1.8
Summary: Tools to handle Fluidigm IMC data
Home-page: https://github.com/BodenmillerGroup/imctools
License: MIT
Keywords: MCD,OME-TIFF,IMC,CellProfiler
Author: Vito Zanotelli
Author-email: vito.zanotelli@uzh.ch
Requires-Python: >=3.7,<4.0
Classifier: License :: OSI Approved :: MIT License
Classifier: Operating System :: OS Independent
Classifier: Programming Language :: Python
Classifier: Programming Language :: Python :: 3
Classifier: Programming Language :: Python :: 3.7
Classifier: Programming Language :: Python :: 3.8
Classifier: Programming Language :: Python :: 3.9
Requires-Dist: imagecodecs
Requires-Dist: packaging
Requires-Dist: pandas
Requires-Dist: typing_extensions (>=3.7.4.3)
Requires-Dist: xmltodict (>=0.12.0)
Requires-Dist: xtiff (>=0.7.4)
Project-URL: Documentation, https://bodenmillergroup.github.io/imctools
Project-URL: Repository, https://github.com/BodenmillerGroup/imctools
